[
	{
		"listType": "country",
		"list": [
			{
				"id": "US",
				"name": "United States"
			},
			{
				"id": "CA",
				"name": "Canada"
			},
			{
				"id": "AL",
				"name": "Albania"
			}
		]
	},
	{
		"listType": "companies",
		"list": [
			{
				"id": 1,
				"name": "Importer Alpha",
				"countryId": "US",
				"address": "1000 Main Street, Hollywood, FL, 12902"
			},
			{
				"id": 2,
				"name": "Importer Bravo",
				"countryId": "US",
				"address": "222 Summer Street, Mountainview, CA 13431"
			},
			{
				"id": 3,
				"name": "Importer Charlie",
				"countryId": "US",
				"address": "54523 Fairfax Blvd., Fairfax, VA 22030"
			},
			{
				"id": 4,
				"name": "Importer Delta",
				"countryId": "US",
				"address": "1234 Random Address, Charlstown, WV 34241"
			}
		]
	},
	{
		"listType": "suppliers",
		"list": [
			{
				"id": 1,
				"name": "Supplier Alpha",
				"countryId": "US",
				"address": "1000 Main Street, Hollywood, FL, 12902"
			},
			{
				"id": 2,
				"name": "Supplier Bravo",
				"countryId": "US",
				"address": "222 Summer Street, Mountainview, CA 13431"
			},
			{
				"id": 3,
				"name": "Supplier Charlie",
				"countryId": "US",
				"address": "54523 Fairfax Blvd., Fairfax, VA 22030"
			},
			{
				"id": 4,
				"name": "Supplier Delta",
				"countryId": "US",
				"address": "1234 Random Address, Charlstown, WV 34241"
			}
		]
	},
	{
		"listType": "formsMap",
		"list": [
			{
				"id": 1,
				"template": "dcca-import.html",
				"size": "lg"
			},
			{
				"id": 2,
				"template": "approval-default.html"
			},
			{
				"id": 3,
				"template": "confirmation-default.html"
			},
			{
				"id": 4,
				"template": "dcca-import-static.html"
			}
		]
	},
	{
		"listType": "approvalCodes",
		"list": [
			{
				"id": 1,
				"name": "Approved"
			},
			{
				"id": 2,
				"name": "Rejected"
			},
			{
				"id": 3,
				"name": "Additional Information Required"
			}
		]
	},
	{
		"listType": "formFields",
		"list": [
			{
				"internal": "submitter",
				"display": "Submitter",
				"description": "The person who submitted the application."
			},
			{
				"internal": "applicant",
				"display": "Applicant",
				"description": "The person or company applying for the licence."
			},
			{
				"internal": "hsCode",
				"display": "HS Code",
				"description": "The unique code for the commodity."
			},
			{
				"internal": "description",
				"display": "Description",
				"description": "Description of the item."
			},
			{
				"internal": "unitType",
				"display": "Unit of Sale",
				"description": "The unit of sale."
			},
			{
				"internal": "quantity",
				"display": "Quantity",
				"description": "The quantity in units of sale."
			},
			{
				"internal": "pricePerUnit",
				"display": "Price Per Unit",
				"description": "In Barbados Dollars"
			},
			{
				"internal": "cifValue",
				"display": "Customs Value",
				"description": "In Barbados Dollars"
			},
			{
				"internal": "origin",
				"display": "Country of Origin",
				"description": "The country from where the goods originated."
			},
			{
				"internal": "countryConsigned",
				"display": "Country whence Consigned",
				"description": "The country where the goods were consigned."
			},
			{
				"internal": "supplier",
				"display": "Supplier",
				"description": "The name of the Supplier of the goods."
			},
			{
				"internal": "expectedArrival",
				"display": "Expected Date of Arrival",
				"description": "The date that the goods will arrive in Barbados."
			}
		]
	}
]